debugprint/__init__.py
debugprint/debugprint.py
test/__init__.py
test/test_debugprint.py
test/test_env_var_handling.py
debugprint-0.1.10.dist-info/LICENSE
debugprint-0.1.10.dist-info/METADATA
debugprint-0.1.10.dist-info/WHEEL
debugprint-0.1.10.dist-info/top_level.txt
debugprint-0.1.10.dist-info/RECORD
