Metadata-Version: 2.1
Name: debugprint
Version: 0.1.10
Summary: A clone of the npm debug module with ability to implement custom formatting
Home-page: https://github.com/phil-arh/debugprint
Author: Phil Howe
Author-email: philhbusiness@gmail.com
License: Apache 2.0
Keywords: debug print
Platform: UNKNOWN
